fencepy/__init__.py
fencepy/_version.py
fencepy/fencepy.conf.default
fencepy/helpers.py
fencepy/main.py
fencepy/plugins.py
fencepy-0.7.2.dist-info/DESCRIPTION.rst
fencepy-0.7.2.dist-info/METADATA
fencepy-0.7.2.dist-info/RECORD
fencepy-0.7.2.dist-info/WHEEL
fencepy-0.7.2.dist-info/entry_points.txt
fencepy-0.7.2.dist-info/metadata.json
fencepy-0.7.2.dist-info/top_level.txt
