Metadata-Version: 2.0
Name: fencepy
Version: 0.7.2
Summary: Standardized fencing off of python virtual environments on a per-project basis
Home-page: https://github.com/ajk8/fencepy
Author: Adam Kaufman
Author-email: kaufman.blue@gmail.com
License: MIT
Download-URL: https://github.com/ajk8/fencepy/tarball/0.7.2
Keywords: fencepy virtualenv virtual environment development project
Platform: UNKNOWN
Classifier: Development Status :: 4 - Beta
Classifier: Environment :: Console
Classifier: Intended Audience :: Developers
Classifier: License :: OSI Approved :: MIT License
Classifier: Natural Language :: English
Classifier: Operating System :: OS Independent
Classifier: Programming Language :: Python :: 2
Classifier: Programming Language :: Python :: 2.6
Classifier: Programming Language :: Python :: 2.7
Classifier: Programming Language :: Python :: 3
Classifier: Programming Language :: Python :: 3.3
Classifier: Programming Language :: Python :: 3.4
Classifier: Programming Language :: Python :: 3.5
Classifier: Topic :: Software Development
Classifier: Topic :: Software Development :: Build Tools
Classifier: Topic :: Software Development :: Testing
Classifier: Topic :: System :: Shells
Classifier: Topic :: Terminals
Classifier: Topic :: Terminals :: Terminal Emulators/X Terminals
Classifier: Topic :: Utilities
Requires-Dist: docopt (>=0.6.2)
Requires-Dist: funcy (>=1.5)
Requires-Dist: psutil (>=2.2.1)
Requires-Dist: six (>=1.10.0)
Requires-Dist: virtualenv (>=12.0.7)
